{
	"id": "93f4561d-f90b-4fa7-b337-831c75d96e8b",
	"name": "Local-Unitech",
	"values": [
		{
			"key": "localbaseurl",
			"value": "http://localhost:8080/api/v1/unitech-app",
			"type": "default",
			"enabled": true
		},
		{
			"key": "accesstoken",
			"value": "eyJhbGciOiJIUzI1NiJ9.eyJzdWIiOiJFRUVFIiwiaWF0IjoxNzE1NTM0NjYyLCJleHAiOjE3MTU4MzQ2NjJ9.aFvcGXk36TS1Zleel6irBR-RubQ_6abkvg1VYOPHfTM",
			"type": "default",
			"enabled": true
		}
	],
	"_postman_variable_scope": "environment",
	"_postman_exported_at": "2024-05-12T18:14:11.713Z",
	"_postman_exported_using": "Postman/11.0.11"
}